heumTest/test1.py
heumTest/test2.py
heumTest-0.0.0.2.dist-info/METADATA
heumTest-0.0.0.2.dist-info/WHEEL
heumTest-0.0.0.2.dist-info/top_level.txt
heumTest-0.0.0.2.dist-info/RECORD
