Metadata-Version: 2.1
Name: heumTest
Version: 0.0.0.2
Summary: My First Test Package
Home-page: https://lingua.blog.me/...
Author: Sukjae Choi
Author-email: lingua72@gmail.com
License: MIT
Platform: UNKNOWN
Requires-Python: >=3
